nixtract-slurm/__init__.py
nslurm/__init__.py
nslurm/nslurm.py
tests/__init__.py
tests/resource_tests.py
tests/tests.py
nixtract_slurm-0.1.3.dist-info/LICENSE
nixtract_slurm-0.1.3.dist-info/METADATA
nixtract_slurm-0.1.3.dist-info/WHEEL
nixtract_slurm-0.1.3.dist-info/entry_points.txt
nixtract_slurm-0.1.3.dist-info/top_level.txt
nixtract_slurm-0.1.3.dist-info/RECORD
