Metadata-Version: 2.1
Name: nixtract-slurm
Version: 0.1.3
Summary: A wrapper for nixtract that enables SLURM job submission.
Home-page: https://github.com/harveyaa/nixtract-slurm
Author: Annabelle Harvey
Author-email: annabelle.harvey@umontreal.ca
License: MIT
Platform: UNKNOWN
Classifier: Development Status :: 3 - Alpha
Classifier: Topic :: Scientific/Engineering :: Bio-Informatics
Classifier: License :: OSI Approved :: MIT License
